go_template/__init__.py
go_template/utils.py
go_template/wrapper.py
go_template/bind/template.so
go_template-0.0.3.dist-info/LICENSE
go_template-0.0.3.dist-info/METADATA
go_template-0.0.3.dist-info/WHEEL
go_template-0.0.3.dist-info/top_level.txt
go_template-0.0.3.dist-info/RECORD
