Metadata-Version: 2.1
Name: go-template
Version: 0.0.3
Summary: python bindings for go template
Home-page: https://github.com/harsh-98/go-template
Author: harsh
Author-email: harshjniitr@gmail.com
License: MIT
Keywords: golang template bindings wrapper
Platform: UNKNOWN
Classifier: Development Status :: 3 - Alpha
Classifier: Programming Language :: Python :: 2.6
Classifier: Programming Language :: Python :: 2.7
Classifier: Programming Language :: Python :: 3.4
Classifier: Programming Language :: Python :: 3.5
Classifier: Programming Language :: Python :: 3.6
Classifier: Programming Language :: Python :: 3.7
Classifier: License :: OSI Approved :: MIT License
